{
  "date": "2026-03-06",
  "total_scraped_today": 24158,
  "new_links_count": 81,
  "updated_links_count": 17,
  "new_links": [
    {
      "url": "https://www.breachsense.com/breaches/abutriek-service-data-breach/",
      "lastmod": "2026-03-06T00:00:00+00:00",
      "scraped_date": "2026-03-06"
    },
    {
      "url": "https://www.breachsense.com/breaches/alphington-sports-medicine-clinic-data-breach/",
      "lastmod": "2026-03-06T00:00:00+00:00",
      "scraped_date": "2026-03-06"
    },
    {
      "url": "https://www.breachsense.com/breaches/ambicare-health-data-breach/",
      "lastmod": "2026-03-06T00:00:00+00:00",
      "scraped_date": "2026-03-06"
    },
    {
      "url": "https://www.breachsense.com/breaches/applied-products-data-breach/",
      "lastmod": "2026-03-06T00:00:00+00:00",
      "scraped_date": "2026-03-06"
    },
    {
      "url": "https://www.breachsense.com/breaches/atlas-insurance-data-breach/",
      "lastmod": "2026-03-06T00:00:00+00:00",
      "scraped_date": "2026-03-06"
    },
    {
      "url": "https://www.breachsense.com/breaches/cd-oracle-clinic-data-breach/",
      "lastmod": "2026-03-06T00:00:00+00:00",
      "scraped_date": "2026-03-06"
    },
    {
      "url": "https://www.breachsense.com/breaches/cti-coordinators-data-breach/",
      "lastmod": "2026-03-06T00:00:00+00:00",
      "scraped_date": "2026-03-06"
    },
    {
      "url": "https://www.breachsense.com/breaches/design-source-data-breach/",
      "lastmod": "2026-03-06T00:00:00+00:00",
      "scraped_date": "2026-03-06"
    },
    {
      "url": "https://www.breachsense.com/breaches/donjon-singapore-data-breach/",
      "lastmod": "2026-03-06T00:00:00+00:00",
      "scraped_date": "2026-03-06"
    },
    {
      "url": "https://www.breachsense.com/breaches/elc-security-data-breach/",
      "lastmod": "2026-03-06T00:00:00+00:00",
      "scraped_date": "2026-03-06"
    },
    {
      "url": "https://www.breachsense.com/breaches/f-one-data-breach/",
      "lastmod": "2026-03-06T00:00:00+00:00",
      "scraped_date": "2026-03-06"
    },
    {
      "url": "https://www.breachsense.com/breaches/flooring-installation-systems-data-breach/",
      "lastmod": "2026-03-06T00:00:00+00:00",
      "scraped_date": "2026-03-06"
    },
    {
      "url": "https://www.breachsense.com/breaches/jpc-law-data-breach/",
      "lastmod": "2026-03-06T00:00:00+00:00",
      "scraped_date": "2026-03-06"
    },
    {
      "url": "https://www.breachsense.com/breaches/k-and-s-associates-data-breach/",
      "lastmod": "2026-03-06T00:00:00+00:00",
      "scraped_date": "2026-03-06"
    },
    {
      "url": "https://www.breachsense.com/breaches/klein-professional-services-data-breach/",
      "lastmod": "2026-03-06T00:00:00+00:00",
      "scraped_date": "2026-03-06"
    },
    {
      "url": "https://www.breachsense.com/breaches/liteline-data-breach/",
      "lastmod": "2026-03-06T00:00:00+00:00",
      "scraped_date": "2026-03-06"
    },
    {
      "url": "https://www.breachsense.com/breaches/lococos-data-breach/",
      "lastmod": "2026-03-06T00:00:00+00:00",
      "scraped_date": "2026-03-06"
    },
    {
      "url": "https://www.breachsense.com/breaches/market-connections-asia-data-breach/",
      "lastmod": "2026-03-06T00:00:00+00:00",
      "scraped_date": "2026-03-06"
    },
    {
      "url": "https://www.breachsense.com/breaches/medgpt-app-data-breach/",
      "lastmod": "2026-03-06T00:00:00+00:00",
      "scraped_date": "2026-03-06"
    },
    {
      "url": "https://www.breachsense.com/breaches/myfair-data-breach/",
      "lastmod": "2026-03-06T00:00:00+00:00",
      "scraped_date": "2026-03-06"
    },
    {
      "url": "https://www.breachsense.com/breaches/nopa-industriearmaturen-data-breach/",
      "lastmod": "2026-03-06T00:00:00+00:00",
      "scraped_date": "2026-03-06"
    },
    {
      "url": "https://www.breachsense.com/breaches/northstar-ia-data-breach/",
      "lastmod": "2026-03-06T00:00:00+00:00",
      "scraped_date": "2026-03-06"
    },
    {
      "url": "https://www.breachsense.com/breaches/parker-lipman-data-breach/",
      "lastmod": "2026-03-06T00:00:00+00:00",
      "scraped_date": "2026-03-06"
    },
    {
      "url": "https://www.breachsense.com/breaches/rosenberg-vend%C3%B4me-data-breach/",
      "lastmod": "2026-03-06T00:00:00+00:00",
      "scraped_date": "2026-03-06"
    },
    {
      "url": "https://www.breachsense.com/breaches/rowad-modern-engineering-data-breach/",
      "lastmod": "2026-03-06T00:00:00+00:00",
      "scraped_date": "2026-03-06"
    },
    {
      "url": "https://www.breachsense.com/breaches/schaltbau-data-breach/",
      "lastmod": "2026-03-06T00:00:00+00:00",
      "scraped_date": "2026-03-06"
    },
    {
      "url": "https://www.breachsense.com/breaches/tennessee-valley-electric-cooperative-data-breach/",
      "lastmod": "2026-03-06T00:00:00+00:00",
      "scraped_date": "2026-03-06"
    },
    {
      "url": "https://www.breachsense.com/breaches/trionex-data-breach/",
      "lastmod": "2026-03-06T00:00:00+00:00",
      "scraped_date": "2026-03-06"
    },
    {
      "url": "https://www.breachsense.com/breaches/ugo-group-data-breach/",
      "lastmod": "2026-03-06T00:00:00+00:00",
      "scraped_date": "2026-03-06"
    },
    {
      "url": "https://www.breachsense.com/breaches/weston-consulting-data-breach/",
      "lastmod": "2026-03-06T00:00:00+00:00",
      "scraped_date": "2026-03-06"
    },
    {
      "url": "https://www.breachsense.com/breaches/yur-drivers-network-data-breach/",
      "lastmod": "2026-03-06T00:00:00+00:00",
      "scraped_date": "2026-03-06"
    },
    {
      "url": "https://www.breachsense.com/breaches/adidas-group-extranet-data-breach/",
      "lastmod": "2026-03-05T00:00:00+00:00",
      "scraped_date": "2026-03-06"
    },
    {
      "url": "https://www.breachsense.com/breaches/ahmed-mubarak-debt-collection-data-breach/",
      "lastmod": "2026-03-05T00:00:00+00:00",
      "scraped_date": "2026-03-06"
    },
    {
      "url": "https://www.breachsense.com/breaches/alejandro-hernandez-law-data-breach/",
      "lastmod": "2026-03-05T00:00:00+00:00",
      "scraped_date": "2026-03-06"
    },
    {
      "url": "https://www.breachsense.com/breaches/atrium-data-breach/",
      "lastmod": "2026-03-05T00:00:00+00:00",
      "scraped_date": "2026-03-06"
    },
    {
      "url": "https://www.breachsense.com/breaches/ats-group-data-breach/",
      "lastmod": "2026-03-05T00:00:00+00:00",
      "scraped_date": "2026-03-06"
    },
    {
      "url": "https://www.breachsense.com/breaches/bautomation-data-breach/",
      "lastmod": "2026-03-05T00:00:00+00:00",
      "scraped_date": "2026-03-06"
    },
    {
      "url": "https://www.breachsense.com/breaches/bc-law-offices-data-breach/",
      "lastmod": "2026-03-05T00:00:00+00:00",
      "scraped_date": "2026-03-06"
    },
    {
      "url": "https://www.breachsense.com/breaches/benz-primus-data-breach/",
      "lastmod": "2026-03-05T00:00:00+00:00",
      "scraped_date": "2026-03-06"
    },
    {
      "url": "https://www.breachsense.com/breaches/bk-group-data-breach/",
      "lastmod": "2026-03-05T00:00:00+00:00",
      "scraped_date": "2026-03-06"
    },
    {
      "url": "https://www.breachsense.com/breaches/bravo-electro-data-breach/",
      "lastmod": "2026-03-05T00:00:00+00:00",
      "scraped_date": "2026-03-06"
    },
    {
      "url": "https://www.breachsense.com/breaches/city-of-hesperia-data-breach/",
      "lastmod": "2026-03-05T00:00:00+00:00",
      "scraped_date": "2026-03-06"
    },
    {
      "url": "https://www.breachsense.com/breaches/cjl-engineering-data-breach/",
      "lastmod": "2026-03-05T00:00:00+00:00",
      "scraped_date": "2026-03-06"
    },
    {
      "url": "https://www.breachsense.com/breaches/community-mosaic-data-breach/",
      "lastmod": "2026-03-05T00:00:00+00:00",
      "scraped_date": "2026-03-06"
    },
    {
      "url": "https://www.breachsense.com/breaches/comtec-international-data-breach/",
      "lastmod": "2026-03-05T00:00:00+00:00",
      "scraped_date": "2026-03-06"
    },
    {
      "url": "https://www.breachsense.com/breaches/cti-bat-data-breach/",
      "lastmod": "2026-03-05T00:00:00+00:00",
      "scraped_date": "2026-03-06"
    },
    {
      "url": "https://www.breachsense.com/breaches/cwpa-data-breach/",
      "lastmod": "2026-03-05T00:00:00+00:00",
      "scraped_date": "2026-03-06"
    },
    {
      "url": "https://www.breachsense.com/breaches/dreamup-data-breach/",
      "lastmod": "2026-03-05T00:00:00+00:00",
      "scraped_date": "2026-03-06"
    },
    {
      "url": "https://www.breachsense.com/breaches/eholo-health-data-breach/",
      "lastmod": "2026-03-05T00:00:00+00:00",
      "scraped_date": "2026-03-06"
    },
    {
      "url": "https://www.breachsense.com/breaches/eiffage-data-breach/",
      "lastmod": "2026-03-05T00:00:00+00:00",
      "scraped_date": "2026-03-06"
    },
    {
      "url": "https://www.breachsense.com/breaches/environmental-air-systems-data-breach/",
      "lastmod": "2026-03-05T00:00:00+00:00",
      "scraped_date": "2026-03-06"
    },
    {
      "url": "https://www.breachsense.com/breaches/eos-technology-solutions-data-breach/",
      "lastmod": "2026-03-05T00:00:00+00:00",
      "scraped_date": "2026-03-06"
    },
    {
      "url": "https://www.breachsense.com/breaches/formula50-data-breach/",
      "lastmod": "2026-03-05T00:00:00+00:00",
      "scraped_date": "2026-03-06"
    },
    {
      "url": "https://www.breachsense.com/breaches/french-ministry-of-agriculture-and-food-sovereignty-data-breach/",
      "lastmod": "2026-03-05T00:00:00+00:00",
      "scraped_date": "2026-03-06"
    },
    {
      "url": "https://www.breachsense.com/breaches/hth-companies-data-breach/",
      "lastmod": "2026-03-05T00:00:00+00:00",
      "scraped_date": "2026-03-06"
    },
    {
      "url": "https://www.breachsense.com/breaches/huffman-insurance-group-data-breach/",
      "lastmod": "2026-03-05T00:00:00+00:00",
      "scraped_date": "2026-03-06"
    },
    {
      "url": "https://www.breachsense.com/breaches/icafe-companies-data-breach/",
      "lastmod": "2026-03-05T00:00:00+00:00",
      "scraped_date": "2026-03-06"
    },
    {
      "url": "https://www.breachsense.com/breaches/institute-for-national-security-studies-data-breach/",
      "lastmod": "2026-03-05T00:00:00+00:00",
      "scraped_date": "2026-03-06"
    },
    {
      "url": "https://www.breachsense.com/breaches/lacoste-data-breach/",
      "lastmod": "2026-03-05T00:00:00+00:00",
      "scraped_date": "2026-03-06"
    },
    {
      "url": "https://www.breachsense.com/breaches/landsteiner-labs-data-breach/",
      "lastmod": "2026-03-05T00:00:00+00:00",
      "scraped_date": "2026-03-06"
    },
    {
      "url": "https://www.breachsense.com/breaches/lincoln-green-brewing-data-breach/",
      "lastmod": "2026-03-05T00:00:00+00:00",
      "scraped_date": "2026-03-06"
    },
    {
      "url": "https://www.breachsense.com/breaches/loozap-data-breach/",
      "lastmod": "2026-03-05T00:00:00+00:00",
      "scraped_date": "2026-03-06"
    },
    {
      "url": "https://www.breachsense.com/breaches/mgr-research-data-breach/",
      "lastmod": "2026-03-05T00:00:00+00:00",
      "scraped_date": "2026-03-06"
    },
    {
      "url": "https://www.breachsense.com/breaches/ng-media-data-breach/",
      "lastmod": "2026-03-05T00:00:00+00:00",
      "scraped_date": "2026-03-06"
    },
    {
      "url": "https://www.breachsense.com/breaches/organisme-pour-la-s%C3%A9curit%C3%A9-de-laviation-civile-data-breach/",
      "lastmod": "2026-03-05T00:00:00+00:00",
      "scraped_date": "2026-03-06"
    },
    {
      "url": "https://www.breachsense.com/breaches/outsourcia-data-breach/",
      "lastmod": "2026-03-05T00:00:00+00:00",
      "scraped_date": "2026-03-06"
    },
    {
      "url": "https://www.breachsense.com/breaches/%C3%B6ztek-group-data-breach/",
      "lastmod": "2026-03-05T00:00:00+00:00",
      "scraped_date": "2026-03-06"
    },
    {
      "url": "https://www.breachsense.com/breaches/pantomath-group-data-breach/",
      "lastmod": "2026-03-05T00:00:00+00:00",
      "scraped_date": "2026-03-06"
    },
    {
      "url": "https://www.breachsense.com/breaches/paolo-dental-data-breach/",
      "lastmod": "2026-03-05T00:00:00+00:00",
      "scraped_date": "2026-03-06"
    },
    {
      "url": "https://www.breachsense.com/breaches/pigler-automation-data-breach/",
      "lastmod": "2026-03-05T00:00:00+00:00",
      "scraped_date": "2026-03-06"
    },
    {
      "url": "https://www.breachsense.com/breaches/praxis-oberhof-data-breach/",
      "lastmod": "2026-03-05T00:00:00+00:00",
      "scraped_date": "2026-03-06"
    },
    {
      "url": "https://www.breachsense.com/breaches/rdb-law-firm-data-breach/",
      "lastmod": "2026-03-05T00:00:00+00:00",
      "scraped_date": "2026-03-06"
    },
    {
      "url": "https://www.breachsense.com/breaches/rt-valve-data-breach/",
      "lastmod": "2026-03-05T00:00:00+00:00",
      "scraped_date": "2026-03-06"
    },
    {
      "url": "https://www.breachsense.com/breaches/salesfloor-data-breach/",
      "lastmod": "2026-03-05T00:00:00+00:00",
      "scraped_date": "2026-03-06"
    },
    {
      "url": "https://www.breachsense.com/breaches/saturn-machine-and-welding-data-breach/",
      "lastmod": "2026-03-05T00:00:00+00:00",
      "scraped_date": "2026-03-06"
    },
    {
      "url": "https://www.breachsense.com/breaches/sport-vision-data-breach/",
      "lastmod": "2026-03-05T00:00:00+00:00",
      "scraped_date": "2026-03-06"
    },
    {
      "url": "https://www.breachsense.com/breaches/tenteks-textile-data-breach/",
      "lastmod": "2026-03-05T00:00:00+00:00",
      "scraped_date": "2026-03-06"
    },
    {
      "url": "https://www.breachsense.com/breaches/thai-hua-group-data-breach/",
      "lastmod": "2026-03-05T00:00:00+00:00",
      "scraped_date": "2026-03-06"
    },
    {
      "url": "https://www.breachsense.com/breaches/university-of-lille-data-breach/",
      "lastmod": "2026-03-05T00:00:00+00:00",
      "scraped_date": "2026-03-06"
    },
    {
      "url": "https://www.breachsense.com/breaches/vision-aero-data-breach/",
      "lastmod": "2026-03-05T00:00:00+00:00",
      "scraped_date": "2026-03-06"
    },
    {
      "url": "https://www.breachsense.com/breaches/wyo-legal-data-breach/",
      "lastmod": "2026-03-05T00:00:00+00:00",
      "scraped_date": "2026-03-06"
    }
  ],
  "updated_links": [
    "https://www.breachsense.com/breaches/",
    "https://www.breachsense.com/breaches/2026/march/",
    "https://www.breachsense.com/breaches/jbs-data-breach/",
    "https://www.breachsense.com/breaches/brockman-injury-lawyer-data-breach/",
    "https://www.breachsense.com/breaches/eni-data-breach/",
    "https://www.breachsense.com/breaches/gci-data-breach/",
    "https://www.breachsense.com/breaches/hopkins-law-data-breach/",
    "https://www.breachsense.com/breaches/law-offices-of-eric-hershler-data-breach/",
    "https://www.breachsense.com/breaches/napolin-accident-injury-lawyer-data-breach/",
    "https://www.breachsense.com/breaches/elad-data-breach/",
    "https://www.breachsense.com/breaches/hawaii-unified-data-breach/",
    "https://www.breachsense.com/breaches/hawaii-unified-data-breach/",
    "https://www.breachsense.com/breaches/ima-data-breach/",
    "https://www.breachsense.com/breaches/bunger-steel-data-breach/",
    "https://www.breachsense.com/breaches/elad-data-breach/",
    "https://www.breachsense.com/breaches/bunger-steel-data-breach/",
    "https://www.breachsense.com/breaches/ima-data-breach/"
  ]
}